bbext/__init__.py
bbext/__main__.py
bbext/blender_utils.py
bbext/constents.py
bbext/package_management.py
blender_extension_builder-1.7.1.dist-info/licenses/LICENSE
blender_extension_builder-1.7.1.dist-info/METADATA
blender_extension_builder-1.7.1.dist-info/WHEEL
blender_extension_builder-1.7.1.dist-info/entry_points.txt
blender_extension_builder-1.7.1.dist-info/top_level.txt
blender_extension_builder-1.7.1.dist-info/RECORD
