Metadata-Version: 2.4
Name: blender-extension-builder
Version: 1.7.1
Summary: Build Blender extensions.
Author: ego-lay-atman-bay
License: GNU GENERAL PUBLIC LICENSE
Project-URL: Homepage, https://github.com/ego-lay-atman-bay/blender-extension-builder
Project-URL: Bug Tracker, https://github.com/ego-lay-atman-bay/blender-extension-builder/issues
Classifier: Programming Language :: Python :: 3
Classifier: License :: OSI Approved :: GNU General Public License v3 (GPLv3)
Classifier: Operating System :: OS Independent
Requires-Python: >=3.10
License-File: LICENSE
Requires-Dist: toml
Requires-Dist: packaging
Requires-Dist: requests
Requires-Dist: pipgrip
Requires-Dist: colorama
Dynamic: license-file
